{"system":{"username":"Moulavi1","password":"Mou@1444","ehajCode":"","country":{"name":"India","arabicName":"الهند","code":"IND","isMission":true,"telCode":"91","code2":"IN"},"writeBack":"","embassy":"","name":"bau","accountId":"saRY4bAqkkjJoACV7i5kaf"},"info":{"pax":3,"caravan":"CLOUD_7mmND1ehv6pLjMHKLgFJpJ","caravanUrl":"","munazim":"munazim","databaseURL":"","accessToken":"","run":1,"cloud":"2022-09-06 03:15:15 pm"},"travellers":[{"slug":"AMEENAHMED MOMIN 13 Male IND","writeBack":"","nationality":{"name":"India","arabicName":"الهند","code":"IND","isMission":true,"telCode":"91","code2":"IN"},"issuer":{"name":"India","arabicName":"الهند","code":"IND","isMission":true,"telCode":"91","code2":"IN"},"name":{"full":"AMEENAHMED MOMIN","given":"AMEENAHMED","first":"AMEENAHMED","last":"MOMIN","father":"","grand":""},"nameArabic":{"given":"","first":"","last":"","father":"","grand":""},"gender":"Male","dob":{"dmy":"20/09/2008","dmmmy":"20-Sep-2008","dd":"20","mm":"09","mmm":"Sep","yyyy":"2008)","age":13},"passIssueDt":{"dmy":"29/09/2021","dmmmy":"29-Sep-2021","dd":"29","mm":"09","mmm":"Sep","yyyy":"2021)"},"passExpireDt":{"dmy":"19/09/2026","dmmmy":"19-Sep-2026","dd":"19","mm":"09","mmm":"Sep","yyyy":"2026)"},"idIssueDt":{"dmy":"","dmmmy":"","dd":"","mm":"","mmm":"","yyyy":""},"idExpireDt":{"dmy":"","dmmmy":"","dd":"","mm":"","mmm":"","yyyy":""},"birthPlace":"","profession":"unknown","address":"","passportNumber":"V3151599","placeOfIssue":"IND","codeline":"P<INDMOMIN<<AMEENAHMED<<<<<<<<<<<<<<<<<<<<<<\nV3151599<0IND0809203M2609197<<<<<<<<<<<<<<00","images":{"photo":"https://firebasestorage.googleapis.com/v0/b/hajonsoft-kea.appspot.com/o/saRY4bAqkkjJoACV7i5kaf%2FphotoUrl%2F1661172319360_fGN5ZWVT2JrxGFrKZqC8KT-V3151599.jpg?alt=media&token=df1bea69-54d4-4538-abb9-89a45a8d226c","passport":"https://firebasestorage.googleapis.com/v0/b/hajonsoft-kea.appspot.com/o/saRY4bAqkkjJoACV7i5kaf%2FpassportScanUrl%2FurgmZNn7xPZKrDydxkV9Jo-AMEEN-AHMED.jpg?alt=media&token=ae799770-712d-4b03-bb22-c294cb263ba0"}},{"slug":"SHAMA PEDDA TIPPA SAMUDRAM 32 Female IND","writeBack":"","nationality":{"name":"India","arabicName":"الهند","code":"IND","isMission":true,"telCode":"91","code2":"IN"},"issuer":{"name":"India","arabicName":"الهند","code":"IND","isMission":true,"telCode":"91","code2":"IN"},"name":{"full":"SHAMA PEDDA TIPPA SAMUDRAM","given":"SHAMA PEDDA TIPPA","first":"SHAMA","last":"SAMUDRAM","father":"PEDDA","grand":"TIPPA"},"nameArabic":{"given":"","first":"","last":"","father":"","grand":""},"gender":"Female","dob":{"dmy":"17/05/1990","dmmmy":"17-May-1990","dd":"17","mm":"05","mmm":"May","yyyy":"1990)","age":32},"passIssueDt":{"dmy":"31/10/2018","dmmmy":"31-Oct-2018","dd":"31","mm":"10","mmm":"Oct","yyyy":"2018)"},"passExpireDt":{"dmy":"30/10/2028","dmmmy":"30-Oct-2028","dd":"30","mm":"10","mmm":"Oct","yyyy":"2028)"},"idIssueDt":{"dmy":"","dmmmy":"","dd":"","mm":"","mmm":"","yyyy":""},"idExpireDt":{"dmy":"","dmmmy":"","dd":"","mm":"","mmm":"","yyyy":""},"profession":"unknown","address":"","passportNumber":"S7639191","placeOfIssue":"IND","codeline":"P<INDPEDDA<TIPPA<SAMUDRAM<<SHAMA<<<<<<<<<<<<\nS7639191<8IND9005178F2810308<<<<<<<<<<<<<<<0","images":{"photo":"https://firebasestorage.googleapis.com/v0/b/hajonsoft-kea.appspot.com/o/saRY4bAqkkjJoACV7i5kaf%2FphotoUrl%2F1661172312789_69RToM1ioNhpfXfyNoWJZh-S7639191.jpg?alt=media&token=e99f2d8d-bce1-4930-94e3-9b9a210d3088","passport":"https://firebasestorage.googleapis.com/v0/b/hajonsoft-kea.appspot.com/o/saRY4bAqkkjJoACV7i5kaf%2FpassportScanUrl%2F6J9f9WYNxcNX9V4NAHXrew-SHAMA.jpg?alt=media&token=a7589845-b89e-4d16-b92e-8d4f3d8c9247"}},{"slug":"HANI FIRDOSE 31 Female IND","writeBack":"","nationality":{"name":"India","arabicName":"الهند","code":"IND","isMission":true,"telCode":"91","code2":"IN"},"issuer":{"name":"India","arabicName":"الهند","code":"IND","isMission":true,"telCode":"91","code2":"IN"},"name":{"full":"HANI FIRDOSE","given":"HANI","first":"HANI","last":"FIRDOSE","father":"","grand":""},"nameArabic":{"given":"","first":"","last":"","father":"","grand":""},"gender":"Female","dob":{"dmy":"03/09/1991","dmmmy":"03-Sep-1991","dd":"03","mm":"09","mmm":"Sep","yyyy":"1991)","age":31},"passIssueDt":{"dmy":"18/11/2013","dmmmy":"18-Nov-2013","dd":"18","mm":"11","mmm":"Nov","yyyy":"2013)"},"passExpireDt":{"dmy":"17/11/2023","dmmmy":"17-Nov-2023","dd":"17","mm":"11","mmm":"Nov","yyyy":"2023)"},"idIssueDt":{"dmy":"","dmmmy":"","dd":"","mm":"","mmm":"","yyyy":""},"idExpireDt":{"dmy":"","dmmmy":"","dd":"","mm":"","mmm":"","yyyy":""},"profession":"unknown","address":"","passportNumber":"L6142911","placeOfIssue":"IND","codeline":"P<IND<<HANI<FIRDOSE<<<<<<<<<<<<<<<<<<<<<<<<<\nL6142911<9IND9109032F2311171<<<<<<<<<<<<<<<0","images":{"photo":"https://firebasestorage.googleapis.com/v0/b/hajonsoft-kea.appspot.com/o/saRY4bAqkkjJoACV7i5kaf%2FphotoUrl%2F1661172316781_bss6F5TPoLAsg3PkRQnxWQ-L6142911.jpg?alt=media&token=0e79f284-405c-4a3d-8e09-1e5a5e9a6303","passport":"https://firebasestorage.googleapis.com/v0/b/hajonsoft-kea.appspot.com/o/saRY4bAqkkjJoACV7i5kaf%2FpassportScanUrl%2Fqam57xULJdbYmjJ5Pw4m7D-HANI-FIRDOSE.jpg?alt=media&token=2e922a1f-99d7-4cbf-a9b3-6454d7f0fcfc"}}]}